Workbook

Sheet Read Me
A1: Assessing Intel's sustainability reporting with TSMC's impact-valuation method
A2: Friday integration workshop | Assessing Sustainability Performance | Built 2 Oct 2026
A4: Purpose | B4: Compare Intel's and TSMC's 2025 quantitative figures and qualitative actions for three impact factors (carbon, water, occupational health & safety), then use TSMC's valuation coefficients to turn Intel's disclosed quantities into monetized impacts (NT$ and US$).
A5: IMPORTANT: page references | B5: The TSMC page numbers in the assignment (carbon pp. 25-26, water pp. 27-29, OHS pp. 38-39) match TSMC's separate 2025 *Sustainability Impact Valuation Report* (IVR), not the main 2025 Sustainability Report (where pp. 25-29 are stakeholder-communication pages and pp. 38-39 are R&D/innovation). The IVR was downloaded from esg.tsmc.com and used here. Raw TSMC activity data (e.g., injury rates, water targets) come from the main report, cited by page.
A6: Documents used | B6: TSMC 2025 Sustainability Impact Valuation Report (IVR): pp. 25-29 (carbon, water), pp. 38-39 (OHS), p. 49 (Integrated P&L), pp. 51-54 & 57-59 (methodology and valuation coefficients). TSMC 2025 Sustainability Report: p. 32 (impact valuation summary), p. 91 (climate targets), pp. 105-106 (water targets), pp. 177-178 (injury statistics). Intel 2025-26 Corporate Responsibility Report: p. 23 (health & safety), pp. 32-39 (climate, water, supply chain), p. 58 (performance data), pp. 60-61 (water inventory), p. 62 (GHG inventory).
A7: How the workbook is organized | B7: Carbon / Water / OHS = side-by-side comparison: Part A quantitative figures, Part B qualitative actions with assessment prompts. TSMC Coefficients = TSMC's published valuation factors plus unit rates implied by its 2025 results (all formulas). Intel Monetization = Intel quantities x TSMC coefficients, with positive / negative / net results per factor and TSMC as a benchmark. TSMC & Intel Trends = 2021-2025 series, including Intel's carbon cost per year at TSMC's annual social cost of carbon. Intel Water by Site / Intel GHG by Site = Intel appendix tables (pp. 60-62), with site-level monetization. Data Gaps = what TSMC's method needs that Intel does not disclose, for assessing Intel's report.
A8: Colour legend | B8: Blue text = hard-coded input from a report. Black = formula. Green = link to another sheet. Yellow fill = assumption or student input you can change (e.g., exchange rate, lost days per case, figures Intel does not disclose). Orange tint = TSMC column; blue tint = Intel column.
A9: Units | B9: TSMC values are in NT$ million (2023 NT$ base, per IVR p. 59). Intel monetized results are shown in both NT$ million and US$ million using the exchange-rate assumption on the TSMC Coefficients sheet. 1 megaliter (ML) = 1,000 m3; 1 billion US gallons = 3.785 million m3.
A10: Key caveats | B10: 1) TSMC's water and OHS figures come from site-specific models (water stress index, DALYs, human-capital approach). The implied unit rates are a simplification students can critique. 2) Intel reports injury RATES, not counts or lost workdays, so case counts are estimated from headcount. 3) Intel 'water restored' and TSMC 'Water Positive' use different definitions (Intel 103% net positive vs TSMC 21% Water Positive achievement rate). They are not like-for-like. 4) Intel Scope 2 is market-based (49,000 t) because Intel buys 99% renewable electricity; location-based is 3,311,000 t.

Sheet Carbon
A1: Factor 1. Carbon (GHG emissions)
A2: TSMC: TSMC 2025 Sustainability Impact Valuation Report (IVR) pp. 25-26 (+ main report p. 91). Intel: report p. 62 (+ pp. 34-36, 58).
A4: Part A. Quantitative figures
A5: Metric | B5: TSMC 2025 | C5: TSMC unit | D5: Intel 2025 | E5: Intel unit | F5: Like-for-like? | G5: Comparability note | H5: TSMC source | I5: Intel source
A6: Scope 1 GHG emissions | B6: 2200000 | C6: tCO2e | D6: 1274000 | E6: tCO2e | F6: Yes | G6: Both GHG Protocol. TSMC reported as 2.2 MtCO2e. | H6: IVR p. 25 | I6: Intel p. 35, p. 62
A7: Scope 2 GHG emissions (market-based) | B7: 13630000 | C7: tCO2e | D7: 49000 | E7: tCO2e | F7: Yes | G7: Gap driven by renewables: Intel 99% renewable electricity vs TSMC 20.1%. | H7: IVR p. 25 | I7: Intel p. 35, p. 62
A8: Scope 2 GHG emissions (location-based) | B8: Not reported in IVR | D8: 3311000 | E8: tCO2e | F8: Partly | G8: Intel's location-based figure shows what its electricity would emit without renewable purchases. | H8: - | I8: Intel p. 35 note 2
A9: Scope 1 + 2 total (valued by TSMC) | B9: 15830000 | C9: tCO2e | D9: 1323000 | E9: tCO2e | F9: Yes | G9: TSMC is ~12x larger; scale differs (TSMC revenue NT$3.81 trillion). | H9: IVR p. 25 | I9: Intel p. 35, p. 58
A10: Scope 3 emissions | B10: Supply-chain GHG valued at NT$39,540m (≈5.2 MtCO2e at TSMC's SCC, implied) | D10: 25053000 | E10: tCO2e | F10: Partly | G10: TSMC values a supply-chain hotspot estimate, not full Scope 3. Intel's total includes 13.65 Mt product use and 10.9 Mt purchased + capital goods. | H10: IVR p. 49 (IP&L) | I10: Intel p. 35
A11: Renewable electricity share | B11: 0.201 | C11: % of electricity | D11: 0.99 | E11: % of electricity | F11: Yes | G11: Intel 100% in US, Europe, Israel, Malaysia, Vietnam, China; 97% Costa Rica; India 0%. | H11: IVR p. 26; TSR p. 91 | I11: Intel pp. 32, 36
A12: Renewable energy used | B12: 57.8 | C12: billion kWh | D12: 10.2 | E12: billion kWh electricity (≈99% renewable) | F12: Partly | G12: Intel figure is total electricity use (chart, p. 36). | H12: IVR p. 25 | I12: Intel p. 36
A13: Total energy use | B13: Not in scope pages | D13: 12 | E13: billion kWh | F13: No | H13: - | I13: Intel p. 58
A14: Energy savings | B14: 0.9 | C14: billion kWh per year (2,141 measures) | D14: 2.7 | E14: billion kWh cumulative 2020-2025 | F14: No | G14: TSMC reports annual savings; Intel reports cumulative savings toward 4 bn kWh by 2030. | H14: IVR p. 26 | I14: Intel p. 34
A15: Cost savings from energy efficiency | B15: 3850 | C15: NT$ million (2025) | D15: 200 | E15: US$ million cumulative since 2020 ($105m invested) | F15: No | G15: Different periods. | H15: IVR p. 26 | I15: Intel p. 34
A16: Monetized external cost of GHG (negative) | B16: -120105 | C16: NT$ million | D16: Not reported | F16: No | G16: Intel does not monetize. See Intel Monetization sheet. | H16: IVR pp. 25-26 | I16: -
A17: Monetized benefit of energy saving + renewables (positive) | B17: 41681 | C17: NT$ million | D17: Not reported | F17: No | G17: TSMC split: energy saving NT$20,364m, renewables NT$21,317m. | H17: IVR pp. 25-26, p. 49 | I17: -
A18: Social cost of carbon applied | B18: 7588 | C18: NT$ (2023) per tCO2e (= US$212 in 2020 $) | D18: None | F18: No | G18: TSMC also lists US$244/t for 2025 (p. 58). | H18: IVR pp. 58-59 | I18: -
A19: Interim target | B19: Scope 1+2 -31% by 2030 (base 2025); Scope 3 -15% by 2030 | D19: Scope 1+2 -10% by 2030 (base 2019); 2025 = -16% | F19: Partly | G19: Different base years. Intel already beats its 2030 milestone; TSMC's targets are SBTi-aligned. | H19: TSR p. 91 | I19: Intel p. 34
A20: Long-term target | B20: Net zero 2050; 100% renewables by 2040 | D20: Net-zero Scope 1+2 by 2040; net-zero upstream Scope 3 by 2050; 100% renewables by 2030 | F20: Yes | G20: Intel's dates are earlier. | H20: TSR p. 91; IVR p. 26 | I20: Intel pp. 33, 36
A21: Emissions intensity trend | B21: GHG per unit of production rose 2% (target -10% missed) | D21: Absolute S1+2 -67% since 2006 peak; up 10% vs 2024 (1.20 to 1.32 Mt) | F21: No | G21: TSMC reports intensity; Intel reports absolute values. | H21: TSR p. 91 | I21: Intel pp. 35, 58
A23: Part B. Qualitative actions
A24: Theme | B24: TSMC action (what TSMC does) | C24: Intel action (what Intel discloses) | D24: Assessment prompt: how does Intel measure up against TSMC's approach?
A25: Valuation method | B25: Environmental P&L using the social cost of carbon (US EPA 2023; IFVI & VBA). Reports external cost, benefits and net value each year, plus cost per wafer-layer and a decoupling rate (8.7%). | C25: No monetization. Reports tonnes, avoided emissions (85% of cumulative Scope 1+2 over a decade) and percent reductions. | D25: Intel discloses enough tonnage data to apply TSMC's SCC directly (best fit of the three factors). The gap is that Intel never states the social cost of its emissions or an intensity metric.
A26: Renewable energy | B26: 7.3 GW long-term contracts; first private company in Taiwan to use offshore wind; PV systems; Green Power pilot program. | C26: 99% renewable electricity via on/off-site generation, utility programs, RECs and PPAs (Green-e certified). | D26: Intel far ahead on share. Ask how much depends on unbundled RECs versus physical PPAs. TSMC monetizes the renewable benefit; Intel does not.
A27: Process emissions (F-GHGs, N2O) | B27: Local scrubbers to cut fluorinated gases and N2O; process gas substitution; piloting carbon capture. | C27: Chemical substitution, abatement, process optimization. F-GHGs are Intel's largest Scope 1 source (658,700 t). | D27: Both focus on abatement. Intel's Scope 1 rose to 1.27 Mt; Intel itself says industrial decarbonization is slow.
A28: Energy efficiency | B28: 2,141 measures (EUV dynamic saving, scrubber standby); five conservation teams; ~900 GWh/yr saved. | C28: ISO 50001 at all manufacturing sites; HVAC, chilled water, heat recovery; 2.7 bn kWh cumulative savings. | D28: Comparable actions. TSMC quantifies annual savings and their monetized benefit; Intel gives cumulative totals.
A29: Targets and science alignment | B29: Committed to SBTi with 2025 base year; submitted plan in 2026. | C29: Says its targets are more ambitious than SBTi but it has not received SBTi approval because of base-year rules. | D29: Students can debate how credible each approach is: TSMC has external validation, Intel has earlier dates.
A30: Supply chain / Scope 3 | B30: Scope 3 targets with key suppliers; NT$160m Supply Chain Carbon Reduction Subsidy; CDP supply-chain program (135 suppliers). | C30: Semiconductor Climate Consortium; Catalyze; SPARC; CDP questionnaire to 130 suppliers (98% response); EPIC program for top 15 suppliers. | D30: Intel's upstream Scope 3 rose 3% in 2025 and is 14% above 2021. TSMC monetizes supply-chain GHG (NT$-39,540m); Intel does not.
A31: Climate resilience / risk | B31: Zero days of production lost to climate events; disaster-response mechanisms. | C31: TCFD-aligned; Climate Transition Action Plan (CTAP); scenario analysis; CDP A- (Climate and Water). | D31: Both are TCFD-aligned. TSMC links resilience to a quantified KPI.

Sheet Water
A1: Factor 2. Water
A2: TSMC: TSMC 2025 Sustainability Impact Valuation Report (IVR) pp. 27-29 (+ main report pp. 105-106). Intel: report pp. 60-61 (+ pp. 37, 58).
A4: Part A. Quantitative figures
A5: Metric | B5: TSMC 2025 | C5: TSMC unit | D5: Intel 2025 | E5: Intel unit | F5: Like-for-like? | G5: Comparability note | H5: TSMC source | I5: Intel source
A6: Fresh water withdrawn / tap water use | B6: 127 | C6: million m3 (tap water) | D6: 42.115 | E6: million m3 (42,115 ML; 11.1 bn gal) | F6: Yes | G6: Both are fresh, purchased water. TSMC ≈3x Intel. | H6: IVR p. 27 | I6: Intel pp. 60-61
A7: Total water withdrawn (all sources) | B7: Not in IVR | D7: 46.615 | E7: million m3 (incl. sea + reclaimed) | F7: No | H7: - | I7: Intel p. 61
A8: Water consumption (withdrawn - discharged) | B8: Not in IVR | D8: 11.298 | E8: million m3 | F8: No | G8: TSMC values 'water consumption' but discloses tap water use as the input. | H8: - | I8: Intel p. 61
A9: Wastewater / water discharged | B9: 98 | C9: million m3 (process wastewater) | D9: 35.317 | E9: million m3 (≈76% to municipal treatment) | F9: Partly | G9: TSMC = process wastewater; Intel = all discharge/return. | H9: IVR p. 28 | I9: Intel pp. 60-61
A10: Water recycled / conserved | B10: 319 | C10: million m3 recycled and reused | D10: 42.348 | E10: million m3 conserved (11.2 bn gal) | F10: Partly | G10: Different definitions (in-fab recycling vs conservation projects). | H10: IVR p. 27 | I10: Intel pp. 37, 61
A11: Reclaimed water use | B11: 22.7 | C11: million m3 | D11: 1.341 | E11: million m3 (reclaimed withdrawal) | F11: Yes | G11: Intel reclaimed water: Ocotillo 1,292 ML + Mission 49 ML. | H11: IVR p. 27 | I11: Intel p. 61
A12: Reclaimed-water substitution rate | B12: 0.18 | C12: % | D12: Not reported | F12: No | H12: IVR p. 29; TSR p. 105 | I12: -
A13: Water restored to watersheds | B13: Not quantified (restoration programs, Verde River plan) | D13: 10.338 | E13: million m3 (2.8 bn gal) | F13: No | H13: TSR p. 106 | I13: Intel pp. 37, 61
A14: Water positive metric | B14: 0.21 | C14: Water Positive achievement rate | D14: 1.03 | E14: net positive water (returned + restored / withdrawn) | F14: No | G14: Definitions differ. Intel counts discharged water as 'returned'; TSMC's rate is stricter. | H14: TSR p. 105 | I14: Intel pp. 37, 58
A15: Unit water consumption trend | B15: +8.8% per wafer-layer vs 2010 (target -2.7% missed) | D15: Fresh water use flat vs 2024; -20% vs 2020 | F15: No | G15: Intensity vs absolute. | H15: TSR p. 105 | I15: Intel p. 37
A16: Water pollution | B16: Composite water pollution index -61.9% | D16: Not reported | F16: No | G16: Intel gives no wastewater quality data. | H16: IVR p. 29 | I16: -
A17: Health risk from water shortage | B17: 10 | C17: DALYs (risk); 27.65 DALYs avoided | D17: Not reported | F17: No | H17: IVR p. 27 | I17: -
A18: Health / ecosystem risk from wastewater heavy metals | B18: 16.5 | C18: DALYs; 14.2 PDF species loss | D18: Not reported | F18: No | H18: IVR p. 28 | I18: -
A19: Sites in high / extremely high water stress | B19: TSMC (China) and TSMC Arizona high-risk (WRI Aqueduct) | D19: Israel (3), Arizona (2), India: extremely high; Chengdu, Rio Rancho: high | F19: Partly | G19: Water stress is central to TSMC's valuation. See Intel Water by Site. | H19: TSR p. 106 | I19: Intel pp. 60-61
A20: Monetized cost of water consumption (negative) | B20: -5709 | C20: NT$ million | D20: Not reported | F20: No | H20: IVR p. 27, p. 49 | I20: -
A21: Monetized cost of wastewater discharge (negative) | B21: -573 | C21: NT$ million | D21: Not reported | F21: No | H21: IVR p. 28 | I21: -
A22: Monetized benefit of water saving + reclaimed water (positive) | B22: 16151 | C22: NT$ million | D22: Not reported | F22: No | G22: Split: water-saving NT$15,135m; reclaimed NT$1,016m. | H22: IVR pp. 27, 29, 49 | I22: -
A23: Target | B23: Water Positive >65% by 2030; 100% by 2040 | D23: Net positive water and 60 bn gal conserved (cumulative from 2020) by 2030; 57.9 bn achieved | F23: Partly | H23: TSR p. 105; IVR p. 29 | I23: Intel p. 37
A25: Part B. Qualitative actions
A26: Theme | B26: TSMC action (what TSMC does) | C26: Intel action (what Intel discloses) | D26: Assessment prompt: how does Intel measure up against TSMC's approach?
A27: Valuation method | B27: EP&L: water consumption weighted by water-stress index and human-development index, giving DALYs (malnutrition, waterborne disease). Valued at US$87,097 per DALY (VSL). Ecosystem loss valued in PDF·m²·yr. Wastewater valued through human toxicity (USEtox) plus SCC for CH4/N2O from treatment. | C27: Volumetric accounting only (withdrawal, discharge, consumption, conserved, restored), site by site with WRI water-stress flags. | D27: Intel's site-level table is rich enough for a stress-weighted approach. The gap: no pollutant data and no health or ecosystem translation.
A28: Reduce | B28: Four measures: cut system discharge loss, reduce facility water use, raise wastewater recycling, improve water production rate. | C28: Water conservation projects saved 11.2 bn gal (+7% vs 2024). | D28: Both report reductions. TSMC's unit water use is rising; Intel's absolute use is flat.
A29: Reuse / alternative sources | B29: Reclaimed water now in advanced processes (18% substitution); desalinated seawater; Arizona reclaimed-water plant with near-zero liquid discharge. | C29: Reuse through on-site treatment; reclaimed water at Ocotillo and Mission; seawater in Israel. | D29: TSMC reports a substitution KPI; Intel does not.
A30: Restore / replenish | B30: Water Positive goal; JASM groundwater replenishment; planned Verde River restoration; ecological programs. | C30: Funded watershed projects restored 2.8 bn gal; net positive in US, India, Costa Rica. | D30: Intel quantifies restoration well. TSMC does not monetize restoration, so students must decide how to value it.
A31: Water quality | B31: Segregated wastewater treatment; ten-pollutant composite index; discharge above regulatory standards. | C31: Not disclosed in the report (refers to CDP). | D31: A clear disclosure gap for Intel under TSMC's method.
A32: Supply chain | B32: Assists suppliers with water saving (NT$787m benefit valued). | C32: CDP water questionnaire to 77 suppliers in water-stressed regions (97% response). | D32: Intel engages suppliers but gives no outcomes.
A33: Disclosure & assurance | B33: Impact valuation report; Climate and Nature Report. | C33: Water inventory assured by Apex Companies (limited assurance); CDP Water Security A-. | D33: Intel's data assurance is a strength.

Sheet OHS
A1: Factor 3. Occupational health & safety
A2: TSMC: TSMC 2025 Sustainability Impact Valuation Report (IVR) pp. 38-39 (+ main report pp. 177-178). Intel: report p. 58 (+ p. 23).
A4: Part A. Quantitative figures
A5: Metric | B5: TSMC 2025 | C5: TSMC unit | D5: Intel 2025 | E5: Intel unit | F5: Like-for-like? | G5: Comparability note | H5: TSMC source | I5: Intel source
A6: Workforce | B6: 90557 | C6: employees | D6: 85100 | E6: employees (year-end) | F6: Yes | G6: Similar scale. | H6: IVR p. 37 | I6: Intel p. 58
A7: Total hours worked (employees) | B7: 169732698 | C7: hours | D7: Not reported | F7: No | G7: Needed to convert rates to counts. | H7: TSR p. 177 | I7: -
A8: Employee disabling / lost-time injuries | B8: 58 | C8: injuries | D8: Not reported (rate only) | F8: No | H8: IVR p. 39; TSR p. 177 | I8: -
A9: Employee lost workdays | B9: 636 | C9: days | D9: Not reported | F9: No | H9: IVR p. 39; TSR p. 177 | I9: -
A10: Disabling Injury Frequency Rate (FR) | B10: 0.34 | C10: per 1,000,000 hours | D10: - | F10: No | G10: Taiwan OSH Act definition. | H10: TSR p. 177 | I10: -
A11: Lost-time case rate per 200,000 hours (converted) | B11: =B8/B7*200000 -> 0.068342754 | C11: per 100 FTE (calculated) | D11: 0.19 | E11: Days-away case rate per 100 FTE | F11: Approx. | G11: TSMC converted to Intel's OSHA basis = 58 / 169.7m hours x 200,000. Definitions still differ. | H11: Calculated from TSR p. 177 | I11: Intel pp. 23, 58
A12: Recordable injury/illness rate | B12: Not reported | D12: 0.78 | E12: per 100 FTE (OSHA) | F12: No | G12: US semiconductor industry average: 0.9 (2024). | H12: - | I12: Intel pp. 23, 58
A13: Contractor injuries | B13: 48 | C13: injuries; 993 lost days | D13: Not reported | F13: No | H13: IVR p. 39 | I13: -
A14: Contractor fatalities | B14: 1 | C14: fatality (cooling tower maintenance) | D14: Not reported | F14: No | H14: IVR p. 38; TSR p. 178 | I14: -
A15: Sexual harassment | B15: 28 | C15: substantiated cases (45 complaints) | D15: Not reported | F15: No | G15: TSMC includes harassment within OHS valuation. | H15: IVR p. 39 | I15: -
A16: Health management reach | B16: 73734 | C16: employees screened; 22,721 CVD risk cases managed | D16: 26000 | E16: people using on-site fitness centers (930,000 visits) | F16: No | G16: Different programs. | H16: IVR p. 38 | I16: Intel p. 23
A17: Safety training coverage | B17: STOP & FIX culture; immersive simulation training | D17: 0.99 | E17: of workforce completed Safety Always course | F17: No | H17: TSR p. 18 | I17: Intel p. 23
A18: Main injury type | B18: Falls / trips from dropped objects; musculoskeletal injuries from manual handling | D18: Ergonomic / cumulative trauma disorders = 57% of injuries | F18: Partly | H18: IVR p. 39 | I18: Intel p. 23
A19: Monetized: employee injuries (negative) | B19: -1.43 | C19: NT$ million | D19: Not reported | F19: No | H19: IVR pp. 38-39 | I19: -
A20: Monetized: contractor injuries (negative) | B20: -17 | C20: NT$ million | D20: Not reported | F20: No | G20: Separately: NT$1,464m socioeconomic loss from the fatality (human-capital approach). | H20: IVR pp. 38-39 | I20: -
A21: Monetized: sexual harassment (negative) | B21: -56.72 | C21: NT$ million | D21: Not reported | F21: No | H21: IVR pp. 38-39 | I21: -
A22: Monetized: health management (positive) | B22: 274 | C22: NT$ million | D22: Not reported | F22: No | H22: IVR pp. 38-39 | I22: -
A23: Target | B23: Zero-incident workplace; from 2026 health targets = program participation and sick-leave rate | D23: Recordable rate below 0.5 per 100 employees | F23: Partly | H23: IVR pp. 38-39 | I23: Intel pp. 4, 23
A25: Part B. Qualitative actions
A26: Theme | B26: TSMC action (what TSMC does) | C26: Intel action (what Intel discloses) | D26: Assessment prompt: how does Intel measure up against TSMC's approach?
A27: Valuation method | B27: Harvard Business School Impact-Weighted Accounts. Health: attributable CVD risk (3.31-25.8%) to estimate healthcare cost avoided. Injuries: human costs + insurance compensation (HSE 2020; VBA 2022). Fatalities: years of potential life lost x human-capital approach (Tsao et al. 2013). Willingness-to-pay to avoid injury: NT$370m. | C27: Rates only (OSHA recordable and days-away); no monetization. | D27: Weakest fit of the three. Intel gives no counts, lost days, contractor data or fatalities, so its figures must be estimated (see Intel Monetization).
A28: Management system | B28: Occupational safety management system; safety performance indicators; source risk control. | C28: ISO 45001 and ISO 14001 multi-site certification since 2001; third-party audits in 2025. | D28: Intel's certification is a strength; TSMC's indicator design is more outcome-linked.
A29: Safety culture & training | B29: STOP & FIX mindset; immersive simulation training; recognition for high-performing crews. | C29: Safety Always training (99%); Safety Star recognition (200+ honorees). | D29: Comparable.
A30: Contractors & value chain | B30: Cross-organizational construction safety committee; AI site monitoring; joint toolbox meetings; PPE designed for Asian body types; contractor data in scope (expanded to US and Japan in 2025). | C30: EHS policy covers contractors; Responsible Factory Initiative with construction sub-contractors. | D30: Major gap: Intel reports no contractor injury or fatality data, which is TSMC's largest OHS cost.
A31: Health & wellbeing | B31: Five priorities (check-ups, risk management, disease prevention, care, promotion); CVD follow-up; stress surveys and counseling. | C31: Fitness centers, Get Moving challenge, mental wellness program, EAP, on-site clinics, Health for Life Centers. | D31: Intel offers broad programs but reports activity, not health outcomes.
A32: Harassment / psychosocial | B32: Sexual harassment cases investigated, valued and disclosed (28 substantiated). | C32: Not covered in the OHS section. | D32: Disclosure gap for Intel if harassment is treated as an OHS impact, as TSMC does.
A33: Ergonomics | B33: Musculoskeletal injuries addressed through handling posture. | C33: Office Ergonomics Program; office CTD injuries down 22%. | D33: Intel gives more detail on its main injury cause.

Sheet TSMC Coefficients
A1: TSMC valuation coefficients and implied unit rates
A2: Published factors: TSMC 2025 Sustainability Impact Valuation Report (IVR) pp. 58-59. Implied rates = TSMC 2025 monetized value / TSMC 2025 activity data (formulas).
A4: A. Assumptions
A5: Item | B5: Value | C5: Unit | D5: Source / note
A6: Exchange rate, NT$ per US$ (2023 average) | B6: 31.16 | C6: NT$/US$ | D6: Assumption: TSMC states all factors in 2023 NT$ (IVR p. 59), so 2023 average rate used. Change if you prefer a 2025 rate.
A8: B. Published valuation factors (IVR p. 59)
A9: Factor | B9: Value | C9: Unit | D9: Before adjustment | E9: Reference | F9: US$ equivalent
A10: Social cost of carbon (SCC) | B10: 7588 | C10: NT$ (2023) per tCO2e | D10: US$212 (2020 $) per tCO2 | E10: US EPA (2023); IFVI & VBA | F10: =B10/$B$6 -> 243.51733
A11: Cost of human health loss | B11: 2891024 | C11: NT$ (2023) per DALY | D11: US$87,097 (2022 $) per DALY = US$2.7m VSL / 31 life-years | E11: OECD (2025); IFVI & VBA (2026) | F11: =B11/$B$6 -> 92779.974
A12: Cost of ecosystem loss | B12: 26.23 | C12: NT$ (2023) per PDF·m²·yr | D12: EUR 0.635 (2015) per PDF·m²·yr | E12: CE Delft (2018) | F12: =B12/$B$6 -> 0.84178434
A13: SCC by year (US$/tCO2), IVR p. 58
A14: 2021 | B14: 2022 | C14: 2023 | D14: 2024 | E14: 2025
A15: 205 | B15: 223 | C15: 236 | D15: 239 | E15: 244
A17: C. Implied unit rates from TSMC 2025 results
A18: Impact line | B18: TSMC 2025 value (NT$ m) | C18: TSMC 2025 activity | D18: Activity unit | E18: Implied rate (NT$ per unit) | F18: Implied rate (US$ per unit) | G18: Note
A19: Carbon: GHG emissions cost (check vs SCC) | B19: -120105 | C19: 15830000 | D19: tCO2e (Scope 1+2) | E19: =B19*1000000/C19 -> -7587.1762 | F19: =E19/$B$6 -> -243.49089 | G19: IVR pp. 25-26. Reproduces SCC ≈ NT$7,588/t, confirming the method.
A20: Carbon: renewable energy benefit | B20: 21317 | C20: 57.8 | D20: billion kWh renewable | E20: =B20*1000000/C20 -> 3.6880623e+08 | F20: =E20/$B$6 -> 11835887 | G20: IVR p. 49. Per bn kWh. Implied ≈NT$0.37/kWh ≈ 0.05 tCO2e/MWh at SCC: far below a grid emission factor. A discussion point.
A21: Carbon: energy-saving benefit | B21: 20364 | C21: 56 | D21: billion kWh cumulative electricity savings | E21: =B21*1000000/C21 -> 3.6364286e+08 | F21: =E21/$B$6 -> 11670182 | G21: IVR p. 49 & p. 25. Implied ≈NT$0.36/kWh, close to the renewable rate, so TSMC appears to value cumulative savings.
A22: Water: consumption cost | B22: -5709 | C22: 127000000 | D22: m3 tap water used | E22: =B22*1000000/C22 -> -44.952756 | F22: =E22/$B$6 -> -1.442643 | G22: IVR p. 27. TSMC actually uses stress-weighted DALYs + ecosystem loss; this is an average.
A23: Water: wastewater discharge cost | B23: -573 | C23: 98000000 | D23: m3 process wastewater | E23: =B23*1000000/C23 -> -5.8469388 | F23: =E23/$B$6 -> -0.18764245 | G23: IVR p. 28.
A24: Water: water-saving benefit | B24: 15135 | C24: 319000000 | D24: m3 water recycled / reused | E24: =B24*1000000/C24 -> 47.445141 | F24: =E24/$B$6 -> 1.5226297 | G24: IVR pp. 27, 49.
A25: Water: reclaimed-water benefit | B25: 1016 | C25: 22700000 | D25: m3 reclaimed water | E25: =B25*1000000/C25 -> 44.757709 | F25: =E25/$B$6 -> 1.4363835 | G25: IVR pp. 27, 49.
A26: OHS: employee injury cost per lost workday | B26: -1.43 | C26: 636 | D26: lost workdays | E26: =B26*1000000/C26 -> -2248.4277 | F26: =E26/$B$6 -> -72.157499 | G26: IVR p. 39.
A27: OHS: employee injury cost per injury | B27: -1.43 | C27: 58 | D27: injuries | E27: =B27*1000000/C27 -> -24655.172 | F27: =E27/$B$6 -> -791.2443 | G27: IVR p. 39.
A28: OHS: contractor injury cost per lost workday | B28: -17 | C28: 993 | D28: lost workdays | E28: =B28*1000000/C28 -> -17119.839 | F28: =E28/$B$6 -> -549.41717 | G28: IVR p. 39 (48 injuries + 1 fatality).
A29: OHS: socioeconomic loss per fatality | B29: -1464 | C29: 1 | D29: fatality | E29: =B29*1000000/C29 -> -1464000000 | F29: =E29/$B$6 -> -46983312 | G29: IVR p. 38. Human-capital approach (YPLL/WYPLL); reported separately from the NT$17m.
A30: OHS: sexual harassment cost per case | B30: -56.72 | C30: 28 | D30: substantiated cases | E30: =B30*1000000/C30 -> -2025714.3 | F30: =E30/$B$6 -> -65010.086 | G30: IVR p. 39.
A31: OHS: health management benefit per case | B31: 274 | C31: 22721 | D31: CVD risk cases managed | E31: =B31*1000000/C31 -> 12059.328 | F31: =E31/$B$6 -> 387.01311 | G31: IVR p. 39.
A32: OHS: avg lost workdays per employee injury | B32: - | C32: - | D32: days per injury | E32: =C26/C27 -> 10.965517 | F32: n/a | G32: Calculated as 636 / 58. Used to estimate Intel lost days.

Sheet Intel Monetization
A1: Intel 2025 impacts monetized with TSMC's method
A2: Intel quantities (blue) x TSMC coefficients (green links). Yellow = assumption or student input. Positive = benefit to society, negative = cost.
A4: Factor | B4: Impact line | C4: Intel quantity | D4: Unit | E4: Conversion to TSMC unit | F4: Quantity in TSMC unit | G4: TSMC rate (NT$/unit) | H4: Monetized (NT$ m) | I4: Monetized (US$ m) | J4: Included in net? | K4: Method note / Intel source
A5: Carbon | B5: Scope 1 emissions (negative) | C5: 1274000 | D5: tCO2e | E5: 1 | F5: =C5*E5 -> 1274000 | G5: =-'TSMC Coefficients'!$B$10 -> -7588 | H5: =F5*G5/1000000 -> -9667.112 | I5: =H5/'TSMC Coefficients'!$B$6 -> -310.24108 | J5: Yes | K5: Intel p. 62. x SCC.
A6: Carbon | B6: Scope 2 market-based emissions (negative) | C6: 49000 | D6: tCO2e | E6: 1 | F6: =C6*E6 -> 49000 | G6: =-'TSMC Coefficients'!$B$10 -> -7588 | H6: =F6*G6/1000000 -> -371.812 | I6: =H6/'TSMC Coefficients'!$B$6 -> -11.932349 | J6: Yes | K6: Intel p. 62. x SCC.
A7: Carbon | B7: Renewable electricity benefit (positive) | C7: 10.098 | D7: billion kWh renewable electricity | E7: 1 | F7: =C7*E7 -> 10.098 | G7: ='TSMC Coefficients'!$E$20 -> 3.6880623e+08 | H7: =F7*G7/1000000 -> 3724.2053 | I7: =H7/'TSMC Coefficients'!$B$6 -> 119.51878 | J7: Yes | K7: Intel: 10.2 bn kWh electricity (p. 36) x 99% renewable (p. 58). Valued at TSMC's implied rate per bn kWh, as TSMC does.
A8: Carbon | B8: Energy-saving benefit (positive) | C8: 2.7 | D8: billion kWh cumulative savings 2020-2025 | E8: 1 | F8: =C8*E8 -> 2.7 | G8: ='TSMC Coefficients'!$E$21 -> 3.6364286e+08 | H8: =F8*G8/1000000 -> 981.83571 | I8: =H8/'TSMC Coefficients'!$B$6 -> 31.50949 | J8: Yes | K8: Intel p. 34. TSMC values cumulative savings (56 bn kWh), so Intel's cumulative figure is used. Note different start years.
A9: Carbon | B9: MEMO: alternative renewable benefit = (location - market Scope 2) x SCC | C9: 3262000 | D9: tCO2e avoided | E9: 1 | F9: =C9*E9 -> 3262000 | G9: ='TSMC Coefficients'!$B$10 -> 7588 | H9: =F9*G9/1000000 -> 24752.056 | I9: =H9/'TSMC Coefficients'!$B$6 -> 794.35353 | J9: No | K9: Intel p. 35: 3,311,000 - 49,000. Uses grid factors, so it is ~7x the TSMC-rate result. Shows how sensitive the result is to the avoided-emission factor.
A10: Carbon | B10: MEMO: upstream Scope 3 purchased + capital goods (negative) | C10: 10900000 | D10: tCO2e | E10: 1 | F10: =C10*E10 -> 10900000 | G10: =-'TSMC Coefficients'!$B$10 -> -7588 | H10: =F10*G10/1000000 -> -82709.2 | I10: =H10/'TSMC Coefficients'!$B$6 -> -2654.3389 | J10: No | K10: Intel p. 35: 7,672,000 + 3,228,000. TSMC values supply-chain GHG separately (NT$-39,540m), so it is kept out of the operations net.
A11: Water | B11: Fresh water withdrawal / consumption cost (negative) | C11: 42115 | D11: ML fresh water withdrawn | E11: 1000 | F11: =C11*E11 -> 42115000 | G11: ='TSMC Coefficients'!$E$22 -> -44.952756 | H11: =F11*G11/1000000 -> -1893.1853 | I11: =H11/'TSMC Coefficients'!$B$6 -> -60.75691 | J11: Yes | K11: Intel p. 61. Same basis as TSMC 'tap water use'.
A12: Water | B12: MEMO: sensitivity on consumption basis (negative) | C12: 11298 | D12: ML consumed | E12: 1000 | F12: =C12*E12 -> 11298000 | G12: ='TSMC Coefficients'!$E$22 -> -44.952756 | H12: =F12*G12/1000000 -> -507.87624 | I12: =H12/'TSMC Coefficients'!$B$6 -> -16.298981 | J12: No | K12: Intel p. 61. Lower bound if only consumed (not returned) water is valued.
A13: Water | B13: Wastewater discharge cost (negative) | C13: 35317 | D13: ML discharged | E13: 1000 | F13: =C13*E13 -> 35317000 | G13: ='TSMC Coefficients'!$E$23 -> -5.8469388 | H13: =F13*G13/1000000 -> -206.49634 | I13: =H13/'TSMC Coefficients'!$B$6 -> -6.6269684 | J13: Yes | K13: Intel p. 61. Likely an overstatement: ~76% goes to municipal treatment and TSMC's rate reflects process-wastewater toxicity.
A14: Water | B14: Water conservation benefit (positive) | C14: 42348 | D14: ML conserved | E14: 1000 | F14: =C14*E14 -> 42348000 | G14: ='TSMC Coefficients'!$E$24 -> 47.445141 | H14: =F14*G14/1000000 -> 2009.2068 | I14: =H14/'TSMC Coefficients'!$B$6 -> 64.480322 | J14: Yes | K14: Intel p. 61. TSMC water-saving rate.
A15: Water | B15: Reclaimed water use benefit (positive) | C15: 1341 | D15: ML reclaimed water withdrawn | E15: 1000 | F15: =C15*E15 -> 1341000 | G15: ='TSMC Coefficients'!$E$25 -> 44.757709 | H15: =F15*G15/1000000 -> 60.020088 | I15: =H15/'TSMC Coefficients'!$B$6 -> 1.9261902 | J15: Yes | K15: Intel p. 61 (Ocotillo 1,292 + Mission 49).
A16: Water | B16: Watershed restoration benefit (positive, student judgment) | C16: 10338 | D16: ML restored | E16: 1000 | F16: =C16*E16 -> 10338000 | G16: ='TSMC Coefficients'!$E$25 -> 44.757709 | H16: =F16*G16/1000000 -> 462.7052 | I16: =H16/'TSMC Coefficients'!$B$6 -> 14.849332 | J16: Yes | K16: Intel p. 61. TSMC does not value restoration; reclaimed-water rate used as a proxy. Set to 0 to exclude.
A17: OHS | B17: Employee lost-time injury cost (negative) | C17: =C30 -> 1773.0145 | D17: estimated lost workdays | E17: 1 | F17: =C17*E17 -> 1773.0145 | G17: ='TSMC Coefficients'!$E$26 -> -2248.4277 | H17: =F17*G17/1000000 -> -3.9864948 | I17: =H17/'TSMC Coefficients'!$B$6 -> -0.12793629 | J17: Yes | K17: Lost days estimated below (Intel gives rates only).
A18: OHS | B18: Contractor injury cost (negative) | C18: 0 | D18: contractor lost workdays | E18: 1 | F18: =C18*E18 -> 0 | G18: ='TSMC Coefficients'!$E$28 -> -17119.839 | H18: =F18*G18/1000000 -> 0 | I18: =H18/'TSMC Coefficients'!$B$6 -> 0 | J18: Yes | K18: Intel does not disclose. Enter if available.
A19: OHS | B19: Fatality socioeconomic loss (negative) | C19: 0 | D19: fatalities (employees + contractors) | E19: 1 | F19: =C19*E19 -> 0 | G19: ='TSMC Coefficients'!$E$29 -> -1464000000 | H19: =F19*G19/1000000 -> 0 | I19: =H19/'TSMC Coefficients'!$B$6 -> 0 | J19: Yes | K19: Intel does not disclose. Enter if available.
A20: OHS | B20: Sexual harassment cost (negative) | C20: 0 | D20: substantiated cases | E20: 1 | F20: =C20*E20 -> 0 | G20: ='TSMC Coefficients'!$E$30 -> -2025714.3 | H20: =F20*G20/1000000 -> 0 | I20: =H20/'TSMC Coefficients'!$B$6 -> 0 | J20: Yes | K20: Intel does not disclose. Enter if available.
A21: OHS | B21: Health management benefit (positive) | C21: 0 | D21: health risk cases managed | E21: 1 | F21: =C21*E21 -> 0 | G21: ='TSMC Coefficients'!$E$31 -> 12059.328 | H21: =F21*G21/1000000 -> 0 | I21: =H21/'TSMC Coefficients'!$B$6 -> 0 | J21: Yes | K21: Intel reports activity (26,000 fitness users), not managed risk cases. Enter if available.
A23: OHS estimation: converting Intel rates to cases and lost days
B24: Intel employees (year-end 2025) | C24: 85100 | K24: Intel p. 58
B25: Days-away case rate (per 100 FTE) | C25: 0.19 | K25: Intel pp. 23, 58
B26: Recordable rate (per 100 FTE) | C26: 0.78 | K26: Intel pp. 23, 58
B27: Estimated days-away cases | C27: =C24/100*C25 -> 161.69 | K27: Calculated as employees / 100 x rate. Approximation: OSHA rates are per 200,000 hours, not per headcount.
B28: Estimated recordable cases | C28: =C24/100*C26 -> 663.78 | K28: Calculated as employees / 100 x recordable rate
B29: Average lost days per case | C29: ='TSMC Coefficients'!E32 -> 10.965517 | K29: Default = TSMC 636 / 58 = 10.97. Change if you have a better estimate.
B30: Estimated employee lost workdays | C30: =C27*C29 -> 1773.0145 | K30: Calculated as cases x days per case. Feeds the OHS employee line above.
B31: MEMO: cost if all recordables valued at TSMC's per-injury rate (NT$ m) | C31: =C28*'TSMC Coefficients'!E27/1000000 -> -16.36561 | K31: Sensitivity (upper bound).
A33: Summary: Intel monetized impact vs TSMC 2025 (only lines marked 'Yes')
A34: Factor | B34: Intel positive (NT$ m) | C34: Intel negative (NT$ m) | D34: Intel net (NT$ m) | E34: Intel net (US$ m) | F34: TSMC positive (NT$ m) | G34: TSMC negative (NT$ m) | H34: TSMC net (NT$ m) | I34: TSMC net (US$ m) | J34: Intel net as % of TSMC net | K34: TSMC source
A35: Carbon | B35: =SUMIFS($H$5:$H$21,$A$5:$A$21,A35,$J$5:$J$21,"Yes",$H$5:$H$21,">0") -> 4706.041 | C35: =SUMIFS($H$5:$H$21,$A$5:$A$21,A35,$J$5:$J$21,"Yes",$H$5:$H$21,"<0") -> -10038.924 | D35: =B35+C35 -> -5332.883 | E35: =D35/'TSMC Coefficients'!$B$6 -> -171.14515 | F35: 41681 | G35: -120105 | H35: =F35+G35 -> -78424 | I35: =H35/'TSMC Coefficients'!$B$6 -> -2516.8164 | J35: =IFERROR(D35/H35,0) -> 0.06800065 | K35: IVR pp. 25-26
A36: Water | B36: =SUMIFS($H$5:$H$21,$A$5:$A$21,A36,$J$5:$J$21,"Yes",$H$5:$H$21,">0") -> 2531.9321 | C36: =SUMIFS($H$5:$H$21,$A$5:$A$21,A36,$J$5:$J$21,"Yes",$H$5:$H$21,"<0") -> -2099.6817 | D36: =B36+C36 -> 432.25047 | E36: =D36/'TSMC Coefficients'!$B$6 -> 13.871966 | F36: 16151 | G36: -6282 | H36: =F36+G36 -> 9869 | I36: =H36/'TSMC Coefficients'!$B$6 -> 316.72015 | J36: =IFERROR(D36/H36,0) -> 0.043798811 | K36: IVR pp. 27-29 (water consumption -5,709 + wastewater -573; excludes air & waste)
A37: OHS | B37: =SUMIFS($H$5:$H$21,$A$5:$A$21,A37,$J$5:$J$21,"Yes",$H$5:$H$21,">0") -> 0 | C37: =SUMIFS($H$5:$H$21,$A$5:$A$21,A37,$J$5:$J$21,"Yes",$H$5:$H$21,"<0") -> -3.9864948 | D37: =B37+C37 -> -3.9864948 | E37: =D37/'TSMC Coefficients'!$B$6 -> -0.12793629 | F37: 274 | G37: -75.15 | H37: =F37+G37 -> 198.85 | I37: =H37/'TSMC Coefficients'!$B$6 -> 6.3815789 | J37: =IFERROR(D37/H37,0) -> -0.020047749 | K37: IVR pp. 38-39 (-1.43 - 17 - 56.72; excludes NT$1,464m fatality loss)
A38: Total | B38: =SUM(B35:B37) -> 7237.9731 | C38: =SUM(C35:C37) -> -12142.592 | D38: =SUM(D35:D37) -> -4904.619 | E38: =SUM(E35:E37) -> -157.40112 | F38: =SUM(F35:F37) -> 58106 | G38: =SUM(G35:G37) -> -126462.15 | H38: =SUM(H35:H37) -> -68356.15 | I38: =SUM(I35:I37) -> -2193.7147 | J38: =IFERROR(D38/H38,0) -> 0.071750955
A40: • Reading the result: a negative net means Intel's operations impose a net cost on society for that factor, valued with TSMC's coefficients.
A41: • Carbon is the most robust line: Intel's tonnes are directly comparable and TSMC's SCC is fully disclosed.
A42: • Water and OHS use average rates implied by TSMC's results. TSMC's own models are site-specific (water stress, DALYs, human capital), so treat these as first-order estimates and discuss the limits.
A43: • Yellow cells hold figures Intel does not disclose. Leaving them at 0 shows how much of TSMC's framework Intel's report cannot support (see Data Gaps).

Sheet TSMC & Intel Trends
A1: 2021-2025 trends
A2: TSMC: TSMC 2025 Sustainability Impact Valuation Report (IVR) p. 49 (Integrated P&L, NT$ m) and pp. 26, 29. Intel: report p. 58 (performance data summary).
A4: Series | B4: 2021 | C4: 2022 | D4: 2023 | E4: 2024 | F4: 2025 | G4: Unit | H4: Source
A5: TSMC: GHG emissions from operations (negative) | B5: -65695 | C5: -78059 | D5: -95869 | E5: -107736 | F5: -120105 | G5: NT$ m | H5: IVR p. 49
A6: TSMC: benefits from renewable energy use | B6: 5193 | C6: 7398 | D6: 9173 | E6: 13050 | F6: 21317 | G6: NT$ m | H6: IVR p. 49
A7: TSMC: benefits from energy-saving measures | B7: 9278 | C7: 12217 | D7: 14931 | E7: 17289 | F7: 20364 | G7: NT$ m | H7: IVR p. 50
A8: TSMC: supply-chain GHG emissions (negative) | B8: -16168 | C8: -20496 | D8: -19040 | E8: -29876 | F8: -39540 | G8: NT$ m | H8: IVR p. 49
A9: TSMC: water consumption (negative) | B9: -3660 | C9: -4612 | D9: -4539 | E9: -4861 | F9: -5709 | G9: NT$ m | H9: IVR p. 50
A10: TSMC: wastewater discharge (negative) | B10: -375 | C10: -447 | D10: -403 | E10: -417 | F10: -573 | G10: NT$ m | H10: IVR p. 50
A11: TSMC: water-saving measures | B11: 8822 | C11: 10122 | D11: 13513 | E11: 13459 | F11: 15135 | G11: NT$ m | H11: IVR p. 50
A12: TSMC: reclaimed water use | B12: 0 | C12: 0 | D12: 563 | E12: 878 | F12: 1016 | G12: NT$ m | H12: IVR p. 50 (not assessed before 2023)
A13: TSMC: employee health management | B13: 0 | C13: 0 | D13: 388 | E13: 509 | F13: 274 | G13: NT$ m | H13: IVR p. 49 (assessed from 2023)
A14: TSMC: sexual harassment (negative) | B14: -22 | C14: -28 | D14: -47 | E14: -57 | F14: -57 | G14: NT$ m | H14: IVR p. 49
A15: TSMC: employee occupational injuries (negative) | B15: -2 | C15: -1 | D15: -1 | E15: -1 | F15: -1 | G15: NT$ m | H15: IVR p. 49 (rounded)
A16: TSMC: contractor occupational injuries (negative) | B16: -2 | C16: -2 | D16: -16 | E16: -17 | F16: -17 | G16: NT$ m | H16: IVR p. 49 (scope expanded 2025)
... A27: Intel: days-away case rate | B27: 0.2 | C27: 0.22 | D27: 0.16 | E27: 0.17 | F27: 0.19 | G27: per 100 FTE | H27: Intel p. 58
A29: Derived: Intel monetized with TSMC's year-specific social cost of carbon and water rate
A30: Series | B30: 2021 | C30: 2022 | D30: 2023 | E30: 2024 | F30: 2025 | G30: Unit | H30: Method
A31: Intel: Scope 1+2 carbon cost at TSMC's annual SCC (negative) | B31: =-B20*'TSMC Coefficients'!A15 -> -307.5 | C31: =-C20*'TSMC Coefficients'!B15 -> -341.19 | D31: =-D20*'TSMC Coefficients'!C15 -> -210.04 | E31: =-E20*'TSMC Coefficients'!D15 -> -286.8 | F31: =-F20*'TSMC Coefficients'!E15 -> -322.08 | G31: US$ m | H31: Mt x US$/t (SCC 205, 223, 236, 239, 244 per IVR p. 58)
A32: Intel: fresh-water cost at TSMC 2025 implied rate (negative) | B32: =B23*3.785411784*'TSMC Coefficients'!$F$22 -> -78.092269 | C32: =C23*3.785411784*'TSMC Coefficients'!$F$22 -> -59.524876 | D32: =D23*3.785411784*'TSMC Coefficients'!$F$22 -> -57.340477 | E32: =E23*3.785411784*'TSMC Coefficients'!$F$22 -> -60.617076 | F32: =F23*3.785411784*'TSMC Coefficients'!$F$22 -> -60.617076 | G32: US$ m | H32: bn gal x 3.785 = million m3, x TSMC US$/m3. Rate held at 2025 level.

Sheet Intel Water by Site
A1: Intel 2025 water inventory by site (megaliters)
A2: Intel report pp. 60-61. Stress per WRI Aqueduct (2026) as footnoted by Intel. Restored and net positive % are reported by country.
A4: Country | B4: Site | C4: Water stress | D4: Fresh water withdrawn (ML) | E4: Total withdrawn (ML) | F4: Discharged (ML) | G4: Consumed (ML) | H4: Conserved (ML) | I4: Restored (ML, country) | J4: Net positive % (country) | K4: Fresh-water cost at TSMC rate (US$ m)
A5: China | B5: Chengdu | C5: High | D5: 463 | E5: 463 | F5: 170 | G5: 294 | H5: 124 | I5: 0 | J5: 0.37 | K5: =D5*1000*'TSMC Coefficients'!$F$22/1000000 -> -0.66794371
A6: Costa Rica | B6: San Jose | D6: 490 | E6: 490 | F6: 162 | G6: 328 | H6: 0 | I6: 454 | J6: 1.26 | K6: =D6*1000*'TSMC Coefficients'!$F$22/1000000 -> -0.70689507
A7: India | B7: Bangalore: Sarjapur | C7: Extremely high | D7: 105 | E7: 105 | F7: 0 | G7: 105 | H7: 93 | I7: 295 | J7: 2.83 | K7: =D7*1000*'TSMC Coefficients'!$F$22/1000000 -> -0.15147752
A8: Ireland | B8: Leixlip | D8: 10911 | E8: 10911 | F8: 10376 | G8: 535 | H8: 3667 | I8: 0 | J8: 0.95 | K8: =D8*1000*'TSMC Coefficients'!$F$22/1000000 -> -15.740678
A9: Israel | B9: Haifa | C9: Extremely high | D9: 26 | E9: 131 | F9: 52 | G9: 79 | H9: 1 | I9: 0 | J9: 0.52 | K9: =D9*1000*'TSMC Coefficients'!$F$22/1000000 -> -0.037508718
A10: Israel | B10: Petach Tikva | C10: Extremely high | D10: 7 | E10: 35 | F10: 23 | G10: 11 | H10: 1 | K10: =D10*1000*'TSMC Coefficients'!$F$22/1000000 -> -0.010098501
A11: Israel | B11: Qiryat Gat | C11: Extremely high | D11: 757 | E11: 3785 | F11: 1987 | G11: 1798 | H11: 5926 | K11: =D11*1000*'TSMC Coefficients'!$F$22/1000000 -> -1.0920808
A12: Malaysia | B12: Kulim | D12: 1143 | E12: 1143 | F12: 914 | G12: 229 | H12: 183 | I12: 178 | J12: 0.89 | K12: =D12*1000*'TSMC Coefficients'!$F$22/1000000 -> -1.6489409
A13: Malaysia | B13: Penang | D13: 732 | E13: 732 | F13: 585 | G13: 147 | H13: 26 | K13: =D13*1000*'TSMC Coefficients'!$F$22/1000000 -> -1.0560147
A14: Poland | B14: Gdansk | D14: 14 | E14: 14 | F14: 10 | G14: 3 | H14: 3 | I14: 0 | J14: 0.75 | K14: =D14*1000*'TSMC Coefficients'!$F$22/1000000 -> -0.020197002
A15: United States | B15: Arizona: Chandler | C15: Extremely high | D15: 1328 | E15: 1328 | F15: 893 | G15: 435 | H15: 423 | I15: 9411 | J15: 1.08 | K15: =D15*1000*'TSMC Coefficients'!$F$22/1000000 -> -1.9158299
A16: United States | B16: Arizona: Ocotillo | C16: Extremely high | D16: 9028 | E16: 10320 | F16: 7343 | G16: 2976 | H16: 14685 | K16: =D16*1000*'TSMC Coefficients'!$F$22/1000000 -> -13.024181
A17: United States | B17: California: Bowers | D17: 199 | E17: 199 | F17: 113 | G17: 87 | H17: 28 | K17: =D17*1000*'TSMC Coefficients'!$F$22/1000000 -> -0.28708596
A18: United States | B18: California: Folsom | D18: 361 | E18: 361 | F18: 106 | G18: 255 | H18: 0 | K18: =D18*1000*'TSMC Coefficients'!$F$22/1000000 -> -0.52079412
A19: United States | B19: California: Mission | D19: 610 | E19: 659 | F19: 458 | G19: 202 | H19: 0 | K19: =D19*1000*'TSMC Coefficients'!$F$22/1000000 -> -0.88001223
A20: United States | B20: New Mexico: Rio Rancho | C20: High | D20: 4229 | E20: 4229 | F20: 3935 | G20: 291 | H20: 2817 | K20: =D20*1000*'TSMC Coefficients'!$F$22/1000000 -> -6.1009373
A21: United States | B21: Oregon: Aloha | D21: 957 | E21: 957 | F21: 752 | G21: 205 | H21: 209 | K21: =D21*1000*'TSMC Coefficients'!$F$22/1000000 -> -1.3806094
A22: United States | B22: Oregon: Jones Farm | D22: 320 | E22: 320 | F22: 240 | G22: 80 | H22: 12 | K22: =D22*1000*'TSMC Coefficients'!$F$22/1000000 -> -0.46164576
A23: United States | B23: Oregon: Ronler Acres | D23: 10050 | E23: 10050 | F23: 7066 | G23: 2984 | H23: 14046 | K23: =D23*1000*'TSMC Coefficients'!$F$22/1000000 -> -14.498562
A24: Vietnam | B24: Ho Chi Minh City | D24: 388 | E24: 388 | F24: 131 | G24: 256 | H24: 104 | I24: 0 | J24: 0.34 | K24: =D24*1000*'TSMC Coefficients'!$F$22/1000000 -> -0.55974548
A25: Total (calculated) | D25: =SUM(D5:D24) -> 42118 | E25: =SUM(E5:E24) -> 46620 | F25: =SUM(F5:F24) -> 35316 | G25: =SUM(G5:G24) -> 11300 | H25: =SUM(H5:H24) -> 42348 | I25: =SUM(I5:I24) -> 10338 | J25: see reported | K25: =SUM(K5:K24) -> -60.761238
A26: Intel reported total | D26: 42115 | E26: 46615 | F26: 35317 | G26: 11298 | H26: 42348 | I26: 10338 | J26: 1.03
A27: Check (calc - reported; Intel rounds) | D27: =D25-D26 -> 3 | E27: =E25-E26 -> 5 | F27: =F25-F26 -> -1 | G27: =G25-G26 -> 2 | H27: =H25-H26 -> 0 | I27: =I25-I26 -> 0
A29: Share of fresh water withdrawn at high / extremely high stress sites | D29: =SUMIFS(D5:D24,C5:C24,"High")+SUMIFS(D5:D24,C5:C24,"Extremely high") -> 15943 | E29: =D29/D25 -> 0.37853174 | G29: Prompt: TSMC weights water costs by local water stress. How might this change Intel's valuation?

Sheet Intel GHG by Site
A1: Intel 2025 Scope 1 and 2 GHG inventory by site (tCO2e)
A2: Intel report p. 62. Scope 2 market-based. '–' in the report entered as 0.
A4: Country | B4: Site | C4: Fluorinated GHGs | D4: Combustion / fuels | E4: Heat transfer fluids | F4: N2O | G4: Other | H4: Total Scope 1 | I4: Scope 2 (market) | J4: % renewable electricity | K4: Total Scope 1+2 | L4: Carbon cost at TSMC SCC (US$ m)
A5: China | B5: Chengdu | C5: 0 | D5: 100 | E5: 2800 | F5: 0 | G5: 600 | H5: 3600 | I5: 0 | J5: 1 | K5: =H5+I5 -> 3600 | L5: =K5*'TSMC Coefficients'!$F$10/1000000 -> 0.87666239
A6: Costa Rica | B6: San Jose | C6: 0 | D6: 600 | E6: 500 | F6: 0 | G6: 0 | H6: 1100 | I6: 10900 | J6: 0.97 | K6: =H6+I6 -> 12000 | L6: =K6*'TSMC Coefficients'!$F$10/1000000 -> 2.922208
A7: India | B7: Bangalore, Sarjapur | C7: 0 | D7: 600 | E7: 0 | F7: 0 | G7: 1000 | H7: 1600 | I7: 38100 | J7: 0 | K7: =H7+I7 -> 39700 | L7: =K7*'TSMC Coefficients'!$F$10/1000000 -> 9.667638
A8: Ireland | B8: Leixlip | C8: 142100 | D8: 54300 | E8: 200 | F8: 37400 | G8: 1100 | H8: 235200 | I8: 0 | J8: 1 | K8: =H8+I8 -> 235200 | L8: =K8*'TSMC Coefficients'!$F$10/1000000 -> 57.275276
A9: Israel | B9: Haifa | C9: 0 | D9: 0 | E9: 0 | F9: 0 | G9: 900 | H9: 900 | I9: 0 | J9: 1 | K9: =H9+I9 -> 900 | L9: =K9*'TSMC Coefficients'!$F$10/1000000 -> 0.2191656
A10: Israel | B10: Petach Tikva | C10: 0 | D10: 0 | E10: 0 | F10: 0 | G10: 800 | H10: 800 | I10: 0 | J10: 1 | K10: =H10+I10 -> 800 | L10: =K10*'TSMC Coefficients'!$F$10/1000000 -> 0.19481386
A11: Israel | B11: Qiryat Gat | C11: 106000 | D11: 34200 | E11: 62000 | F11: 24600 | G11: 1800 | H11: 228600 | I11: 0 | J11: 1 | K11: =H11+I11 -> 228600 | L11: =K11*'TSMC Coefficients'!$F$10/1000000 -> 55.668062
A12: Malaysia | B12: Kulim | C12: 0 | D12: 200 | E12: 8400 | F12: 0 | G12: 0 | H12: 8600 | I12: 0 | J12: 1 | K12: =H12+I12 -> 8600 | L12: =K12*'TSMC Coefficients'!$F$10/1000000 -> 2.094249
A13: Malaysia | B13: Penang | C13: 0 | D13: 200 | E13: 11100 | F13: 0 | G13: 0 | H13: 11300 | I13: 0 | J13: 1 | K13: =H13+I13 -> 11300 | L13: =K13*'TSMC Coefficients'!$F$10/1000000 -> 2.7517458
A14: Poland | B14: Gdansk | C14: 0 | D14: 1000 | E14: 0 | F14: 0 | G14: 200 | H14: 1200 | I14: 0 | J14: 1 | K14: =H14+I14 -> 1200 | L14: =K14*'TSMC Coefficients'!$F$10/1000000 -> 0.2922208
A15: United States | B15: Arizona: Chandler | C15: 1600 | D15: 10500 | E15: 1100 | F15: 0 | G15: 200 | H15: 13400 | I15: 0 | J15: 1 | K15: =H15+I15 -> 13400 | L15: =K15*'TSMC Coefficients'!$F$10/1000000 -> 3.2631322
A16: United States | B16: Arizona: Ocotillo | C16: 107300 | D16: 93400 | E16: 300 | F16: 41100 | G16: 300 | H16: 242400 | I16: 0 | J16: 1 | K16: =H16+I16 -> 242400 | L16: =K16*'TSMC Coefficients'!$F$10/1000000 -> 59.028601
... A24: Vietnam | B24: Ho Chi Minh City | C24: 0 | D24: 200 | E24: 14000 | F24: 0 | G24: 0 | H24: 14100 | I24: 0 | J24: 1 | K24: =H24+I24 -> 14100 | L24: =K24*'TSMC Coefficients'!$F$10/1000000 -> 3.4335944
A25: Total (calculated) | C25: =SUM(C5:C24) -> 658700 | D25: =SUM(D5:D24) -> 328500 | E25: =SUM(E5:E24) -> 102600 | F25: =SUM(F5:F24) -> 176000 | G25: =SUM(G5:G24) -> 8100 | H25: =SUM(H5:H24) -> 1274100 | I25: =SUM(I5:I24) -> 49000 | K25: =SUM(K5:K24) -> 1323100 | L25: =SUM(L5:L24) -> 322.19778
A26: Intel reported total | C26: 658700 | D26: 328300 | E26: 102700 | F26: 175900 | G26: 8400 | H26: 1274000 | I26: 49000 | K26: 1323000
A27: Check (calc - reported); Intel notes rounding | C27: =C25-C26 -> 0 | D27: =D25-D26 -> 200 | E27: =E25-E26 -> -100 | F27: =F25-F26 -> 100 | G27: =G25-G26 -> -300 | H27: =H25-H26 -> 100 | I27: =I25-I26 -> 0 | K27: =K25-K26 -> 100

Sheet Data Gaps
A1: Assessing Intel's report against TSMC's method: data gaps
A2: What TSMC's valuation needs vs what Intel discloses. Status: Disclosed / Partial / Not disclosed.
A4: Factor | B4: Input TSMC's method needs | C4: Intel status | D4: Where in Intel's report | E4: Effect on monetization | F4: Suggested disclosure improvement
A5: Carbon | B5: Scope 1 and Scope 2 tonnes | C5: Disclosed | D5: pp. 35, 62 (by site and gas) | E5: Can be valued directly with SCC. | F5: -
A6: Carbon | B6: Renewable energy / avoided emissions | C6: Disclosed | D6: p. 35 (location- vs market-based Scope 2) | E6: Benefit can be valued. | F6: -
A7: Carbon | B7: Annual energy savings (kWh) | C7: Partial | D7: p. 34 (cumulative 2.7 bn kWh only) | E7: Energy-saving benefit cannot be valued for 2025. | F7: Report annual kWh saved.
A8: Carbon | B8: Supply-chain GHG hotspot | C8: Disclosed | D8: p. 35 (Scope 3 by category) | E8: Can be valued (kept as memo line). | F8: -
A9: Carbon | B9: Monetized external cost / intensity per unit | C9: Not disclosed | D9: - | E9: Students must compute it. | F9: Publish an EP&L or impact-weighted figure; add intensity per wafer or revenue.
A10: Water | B10: Water withdrawal / consumption by site | C10: Disclosed | D10: pp. 60-61 | E10: Can be valued; site detail supports stress weighting. | F10: -
A11: Water | B11: Water stress index by site | C11: Partial | D11: pp. 60-61 footnotes (WRI category only) | E11: Only categorical weighting is possible. | F11: Disclose WSI scores used.
A12: Water | B12: Wastewater pollutant loads (heavy metals, COD, N) | C12: Not disclosed | D12: - | E12: Toxicity-based wastewater cost cannot be replicated; volume proxy used. | F12: Report pollutant loads or a composite water-quality index.
A13: Water | B13: Health impact (DALYs) / ecosystem impact (PDF) | C13: Not disclosed | D13: - | E13: Relies on TSMC's average rates. | F13: -
A14: Water | B14: Reclaimed / recycled water | C14: Partial | D14: p. 61 (reclaimed withdrawals); conserved volumes | E14: Can be valued approximately. | F14: Report in-fab recycling rate.
A15: OHS | B15: Number of injuries and lost workdays | C15: Not disclosed | D15: pp. 23, 58 (rates only) | E15: Must estimate from headcount x rate. | F15: Report counts, hours worked and lost days.
... A18: OHS | B18: Health-program outcomes (risk cases managed) | C18: Partial | D18: p. 23 (activity: fitness visits, wellness) | E18: Health benefit cannot be valued. | F18: Report outcome metrics.
A20: Coverage score | B20: Share of TSMC inputs Intel fully discloses | C20: =COUNTIF(C5:C18,"Disclosed")/COUNTA(C5:C18) -> 0.28571429
B21: Carbon: fully disclosed | C21: =COUNTIFS(A5:A18,"Carbon",C5:C18,"Disclosed")/COUNTIF(A5:A18,"Carbon") -> 0.6
B22: Water: fully disclosed | C22: =COUNTIFS(A5:A18,"Water",C5:C18,"Disclosed")/COUNTIF(A5:A18,"Water") -> 0.2
B23: OHS: fully disclosed | C23: =COUNTIFS(A5:A18,"OHS",C5:C18,"Disclosed")/COUNTIF(A5:A18,"OHS") -> 0
